odoo9_addon_project_issue_code-9.0.1.0.0.99.dev4-py2.7-nspkg.pth
odoo9_addon_project_issue_code-9.0.1.0.0.99.dev4.dist-info/DESCRIPTION.rst
odoo9_addon_project_issue_code-9.0.1.0.0.99.dev4.dist-info/METADATA
odoo9_addon_project_issue_code-9.0.1.0.0.99.dev4.dist-info/RECORD
odoo9_addon_project_issue_code-9.0.1.0.0.99.dev4.dist-info/WHEEL
odoo9_addon_project_issue_code-9.0.1.0.0.99.dev4.dist-info/metadata.json
odoo9_addon_project_issue_code-9.0.1.0.0.99.dev4.dist-info/namespace_packages.txt
odoo9_addon_project_issue_code-9.0.1.0.0.99.dev4.dist-info/top_level.txt
odoo_addons/project_issue_code/README.rst
odoo_addons/project_issue_code/__init__.py
odoo_addons/project_issue_code/__openerp__.py
odoo_addons/project_issue_code/hooks.py
odoo_addons/project_issue_code/data/project_issue_sequence.xml
odoo_addons/project_issue_code/i18n/bg.po
odoo_addons/project_issue_code/i18n/de.po
odoo_addons/project_issue_code/i18n/es.po
odoo_addons/project_issue_code/i18n/fr.po
odoo_addons/project_issue_code/i18n/hr.po
odoo_addons/project_issue_code/i18n/it.po
odoo_addons/project_issue_code/i18n/project_issue_code.pot
odoo_addons/project_issue_code/i18n/pt.po
odoo_addons/project_issue_code/i18n/pt_BR.po
odoo_addons/project_issue_code/i18n/pt_PT.po
odoo_addons/project_issue_code/i18n/sk.po
odoo_addons/project_issue_code/i18n/sl.po
odoo_addons/project_issue_code/i18n/zh_CN.po
odoo_addons/project_issue_code/models/__init__.py
odoo_addons/project_issue_code/models/project_issue.py
odoo_addons/project_issue_code/static/description/icon.png
odoo_addons/project_issue_code/tests/__init__.py
odoo_addons/project_issue_code/tests/test_project_issue_code.py
odoo_addons/project_issue_code/views/project_issue_view.xml
